provider/__init__.py
provider/home_shopping_crawler.py
provider/naver_datalab_carwler.py
utils/__init__.py
utils/chrome_util.py
keyword_collector-0.0.1.dist-info/METADATA
keyword_collector-0.0.1.dist-info/WHEEL
keyword_collector-0.0.1.dist-info/top_level.txt
keyword_collector-0.0.1.dist-info/RECORD
